text_curation/__init__.py
text_curation/_api.py
text_curation/curator.py
text_curation/registry.py
text_curation/blocks/__init__.py
text_curation/blocks/base.py
text_curation/blocks/normalization.py
text_curation/blocks/redaction.py
text_curation/blocks/deduplication/__init__.py
text_curation/blocks/deduplication/exact_paragraph.py
text_curation/blocks/filtering/__init__.py
text_curation/blocks/filtering/signal_based.py
text_curation/blocks/formatting/__init__.py
text_curation/blocks/formatting/code_safe.py
text_curation/blocks/formatting/paragraph.py
text_curation/blocks/structure/__init__.py
text_curation/blocks/structure/basic.py
text_curation/core/annotations.py
text_curation/core/document.py
text_curation/core/pipeline.py
text_curation/core/report.py
text_curation/core/signals.py
text_curation/profiles/__init__.py
text_curation/profiles/base.py
text_curation/profiles/llm_pretrain_v1.py
text_curation/profiles/web_common_v1.py
text_curation/reports/__init__.py
text_curation/reports/aggregate.py
text_curation/reports/summary.py
text_curation-1.4.0.dist-info/licenses/LICENSE
text_curation-1.4.0.dist-info/METADATA
text_curation-1.4.0.dist-info/WHEEL
text_curation-1.4.0.dist-info/top_level.txt
text_curation-1.4.0.dist-info/RECORD
