Metadata-Version: 2.4
Name: text-curation
Version: 1.4.0
Summary: Profile-based text curation pipelines for Hugging Face Datasets
Author-email: Dhiraj Patil <patildhiraj2357@gmail.com>
License:                                  Apache License
Project-URL: Homepage, https://github.com/Dhiraj309/text-curation
Project-URL: Repository, https://github.com/Dhiraj309/text-curation
Project-URL: Issues, https://github.com/Dhiraj309/text-curation/issues
Keywords: huggingface,datasets,nlp,text-preprocessing,text-cleaning,llm,data-curation,cleantext,textcleaning,curation
Classifier: Development Status :: 3 - Alpha
Classifier: Intended Audience :: Science/Research
Classifier: Intended Audience :: Developers
Classifier: License :: OSI Approved :: Apache Software License
Classifier: Programming Language :: Python :: 3
Classifier: Programming Language :: Python :: 3.9
Classifier: Programming Language :: Python :: 3.10
Classifier: Programming Language :: Python :: 3.11
Classifier: Topic :: Scientific/Engineering :: Artificial Intelligence
Classifier: Topic :: Text Processing
Requires-Python: >=3.9
License-File: LICENSE
Requires-Dist: datasets>=2.16.0
Provides-Extra: dev
Requires-Dist: pytest>=7.0; extra == "dev"
Requires-Dist: pytest-cov; extra == "dev"
Requires-Dist: ruff>=0.1.0; extra == "dev"
Requires-Dist: black>=23.0; extra == "dev"
Requires-Dist: mypy>=1.5; extra == "dev"
Requires-Dist: pre-commit; extra == "dev"
Provides-Extra: docs
Requires-Dist: mkdocs; extra == "docs"
Requires-Dist: mkdocs-material; extra == "docs"
Dynamic: license-file
